{"cameraMode":{"drawMode":0,"name":"Shaded","section":"Shading Mode"},"sceneLighting":true,"audioPlay":false,"sceneViewState":{"showFog":true,"showMaterialUpdate":false,"showSkybox":true,"showFlares":true,"showImageEffects":true,"showParticleSystems":true,"showVisualEffectGraphs":true,"m_FxEnabled":true},"in2DMode":false,"pivot":{"x":-5.3836774826049809,"y":3.293640613555908,"z":4.103065013885498},"rotation":{"x":-0.04932618886232376,"y":-0.7314527630805969,"z":0.052813269197940829,"w":-0.6783443093299866},"size":1.2247449159622193,"orthographic":false}